kickpy/VERSION
kickpy/__init__.py
kickpy/_http.py
kickpy/client.py
kickpy/enum.py
kickpy/meta.py
kickpy/models.py
tests/__init__.py
tests/test_test.py
pykick-0.1.1b0.dist-info/METADATA
pykick-0.1.1b0.dist-info/WHEEL
pykick-0.1.1b0.dist-info/top_level.txt
pykick-0.1.1b0.dist-info/RECORD
