Metadata-Version: 2.4
Name: pykick
Version: 0.1.1b0
Summary: A Python library for interacting with the Kick streaming platform API.
Home-page: https://github.com/pavalso/kick.py
Author: Pavalso
License: MIT
Project-URL: Documentation, https://kickpy.readthedocs.io
Project-URL: Source, https://github.com/pavalso/kick.py
Keywords: kick streaming python api library
Classifier: Development Status :: 4 - Beta
Classifier: Intended Audience :: Developers
Classifier: License :: OSI Approved :: MIT License
Classifier: Programming Language :: Python :: 3.10
Classifier: Programming Language :: Python :: 3.11
Requires-Python: >=3.10
Requires-Dist: pydantic
Requires-Dist: pyee
Requires-Dist: aiohttp
Requires-Dist: authlib
Requires-Dist: cryptography
Requires-Dist: packaging
Dynamic: author
Dynamic: classifier
Dynamic: description
Dynamic: description-content-type
Dynamic: home-page
Dynamic: keywords
Dynamic: license
Dynamic: project-url
Dynamic: requires-dist
Dynamic: requires-python
Dynamic: summary
